wait_for_dep/VERSION
wait_for_dep/__init__.py
wait_for_dep/wait_for_dep.py
wait_for_dep/checks/__init__.py
wait_for_dep/checks/amqp.py
wait_for_dep/checks/elasticsearch.py
wait_for_dep/checks/http.py
wait_for_dep/checks/https.py
wait_for_dep/checks/kafka.py
wait_for_dep/checks/memcached.py
wait_for_dep/checks/mongodb.py
wait_for_dep/checks/mysql.py
wait_for_dep/checks/postgres.py
wait_for_dep/checks/postgresql.py
wait_for_dep/checks/psql.py
wait_for_dep/checks/redis.py
wait_for_dep/checks/rediss.py
wait_for_dep/checks/tcp.py
wait_for_dep/checks/unix.py
wait_for_dep-0.5.0.dist-info/LICENSE
wait_for_dep-0.5.0.dist-info/METADATA
wait_for_dep-0.5.0.dist-info/WHEEL
wait_for_dep-0.5.0.dist-info/entry_points.txt
wait_for_dep-0.5.0.dist-info/top_level.txt
wait_for_dep-0.5.0.dist-info/RECORD
