Metadata-Version: 2.2
Name: wait-for-dep
Version: 0.5.0
Summary: Waits for dependencies before running the app
Home-page: http://github.com/wlatanowicz/wait-for-dep
Author: Wiktor Latanowicz
Author-email: wait-for-dep@wiktor.latanowicz.com
License: MIT
Classifier: Programming Language :: Python :: 3
Classifier: License :: OSI Approved :: MIT License
Classifier: Operating System :: OS Independent
Requires-Python: >=3.6
License-File: LICENSE
Requires-Dist: requests>=2.21.0
Provides-Extra: kafka
Requires-Dist: kafka-python; extra == "kafka"
Provides-Extra: memcached
Requires-Dist: python3-memcached; extra == "memcached"
Provides-Extra: mysql
Requires-Dist: mysql-connector-python; extra == "mysql"
Provides-Extra: psycopg3
Requires-Dist: psycopg[binary]>=3.0; extra == "psycopg3"
Provides-Extra: postgres
Requires-Dist: psycopg2-binary; extra == "postgres"
Provides-Extra: rabbitmq
Requires-Dist: pika; extra == "rabbitmq"
Provides-Extra: redis
Requires-Dist: redis; extra == "redis"
Provides-Extra: websockets
Requires-Dist: websocket-server; extra == "websockets"
Provides-Extra: mongodb
Requires-Dist: pymongo; extra == "mongodb"
Dynamic: author
Dynamic: author-email
Dynamic: classifier
Dynamic: description
Dynamic: description-content-type
Dynamic: home-page
Dynamic: license
Dynamic: provides-extra
Dynamic: requires-dist
Dynamic: requires-python
Dynamic: summary
